Metadata-Version: 2.1
Name: p01.checker
Version: 0.5.15
Summary: Python, ZCML, PT, HTML, JS, CSS source checking/linting
Home-page: http://pypi.python.org/pypi/p01.checker
Author: Adam Groszer, Roger Ineichen, Projekt01 GmbH
Author-email: dev@projekt01.ch
License: ZPL 2.1
Keywords: Zope3 z3c p01 checker pyflakes lint
Platform: UNKNOWN
Classifier: Development Status :: 4 - Beta
Classifier: Environment :: Web Environment
Classifier: Intended Audience :: Developers
Classifier: License :: OSI Approved :: Zope Public License
Classifier: Programming Language :: Python
Classifier: Programming Language :: Python :: 2
Classifier: Programming Language :: Python :: 3
Classifier: Natural Language :: English
Classifier: Operating System :: OS Independent
Classifier: Topic :: Internet :: WWW/HTTP
Classifier: Framework :: Zope3
Provides-Extra: cssutils
Provides-Extra: test
